tx/__init__.py
tx/cli.py
tx/assets/example.txt
wormhole_tx-1.1.6.dist-info/licenses/LICENSE
wormhole_tx-1.1.6.dist-info/METADATA
wormhole_tx-1.1.6.dist-info/WHEEL
wormhole_tx-1.1.6.dist-info/entry_points.txt
wormhole_tx-1.1.6.dist-info/top_level.txt
wormhole_tx-1.1.6.dist-info/RECORD
