Metadata-Version: 2.4
Name: wormhole-tx
Version: 1.1.6
Summary: Front end for wormhole, easier and more secure!
Home-page: https://github.com/zackees/tx
Maintainer: Zachary Vorhies
License: BSD 3-Clause License
Keywords: template-python-cmd
Classifier: Programming Language :: Python :: 3
Requires-Python: >=3.10
License-File: LICENSE
Requires-Dist: magic-wormhole>=0.18.0
Requires-Dist: colorama>=0.4.6
Dynamic: home-page
Dynamic: license-file
Dynamic: maintainer
